leaky_bucket_error_count.py
setup.py
leaky_bucket_error_count.egg-info/PKG-INFO
leaky_bucket_error_count.egg-info/SOURCES.txt
leaky_bucket_error_count.egg-info/dependency_links.txt
leaky_bucket_error_count.egg-info/top_level.txt