Metadata-Version: 1.1
Name: leaky-bucket-error-count
Version: 0.1.0
Summary: A leaky bucket type of exception counter
Home-page: https://github.com/okurz/leaky_bucket_error_count
Author: Oliver Kurz
Author-email: o.kurz@gmx.de
License: UNKNOWN
Platform: UNKNOWN
Classifier: Programming Language :: Python
Classifier: Programming Language :: Python :: 3
Classifier: Development Status :: 5 - Production/Stable
Classifier: Environment :: Other Environment
Classifier: Intended Audience :: Developers
Classifier: Intended Audience :: System Administrators
Classifier: License :: OSI Approved :: MIT License
Classifier: Operating System :: OS Independent
Classifier: Topic :: Software Development :: Libraries :: Python Modules
